marhex/__init__.py
marhex/Converters/__init__.py
marhex/Converters/lang_num.py
marhex/ServerInfo/__init__.py
marhex/ServerInfo/network.py
marhex/Validators/__init__.py
marhex/Validators/is_iter.py
marhex/Validators/mobile_phone_number.py
marhex/Validators/national_code.py
marhex-1.3.5.dist-info/LICENSE
marhex-1.3.5.dist-info/METADATA
marhex-1.3.5.dist-info/WHEEL
marhex-1.3.5.dist-info/top_level.txt
marhex-1.3.5.dist-info/RECORD
